djicot/__init__.py
djicot/classes.py
djicot/commands.py
djicot/constants.py
djicot/dji_functions.py
djicot/functions.py
djicot-1.1.2.dist-info/licenses/LICENSE
djicot-1.1.2.dist-info/METADATA
djicot-1.1.2.dist-info/WHEEL
djicot-1.1.2.dist-info/entry_points.txt
djicot-1.1.2.dist-info/top_level.txt
djicot-1.1.2.dist-info/RECORD
