Metadata-Version: 2.4
Name: djicot
Version: 1.1.2
Summary: Geolocate, detect, track & identify DJI Drone sUAS data with TAK.
Home-page: https://github.com/snstac/djicot
Maintainer: Greg Albrecht <oss@undef.net>
Maintainer-email: oss@undef.net
License: Apache 2.0
Project-URL: CI: GitHub Actions, https://github.com/snstac/djicot/actions
Project-URL: GitHub: issues, https://github.com/snstac/djicot/issues
Project-URL: GitHub: repo, https://github.com/snstac/djicot
Keywords: Cursor on Target,CoT,ATAK,TAK,WinTAK,TAK,TAK Server,DJI,UAS,UAV,Drones,Drone ID,OcuSync
Classifier: License :: OSI Approved :: Apache Software License
Classifier: Intended Audience :: Developers
Classifier: Programming Language :: Python
Classifier: Programming Language :: Python :: 3
Classifier: Development Status :: 5 - Production/Stable
Classifier: Operating System :: POSIX
Classifier: Operating System :: MacOS :: MacOS X
Classifier: Operating System :: Microsoft :: Windows
Classifier: Operating System :: OS Independent
Requires-Python: <4,>=3.7
License-File: LICENSE
Requires-Dist: pytak>=5.4.0
Provides-Extra: with-takproto
Requires-Dist: takproto>=2.0.0; extra == "with-takproto"
Provides-Extra: test
Requires-Dist: pytest-asyncio; extra == "test"
Requires-Dist: pytest-cov; extra == "test"
Requires-Dist: pylint; extra == "test"
Requires-Dist: flake8; extra == "test"
Requires-Dist: black; extra == "test"
Requires-Dist: pytak; extra == "test"
Dynamic: license-file
